t5/__init__.py
t5/version.py
t5/data/__init__.py
t5/data/dataset_providers.py
t5/data/dataset_providers_test.py
t5/data/glue_utils.py
t5/data/mixtures.py
t5/data/postprocessors.py
t5/data/postprocessors_test.py
t5/data/preprocessors.py
t5/data/preprocessors_test.py
t5/data/tasks.py
t5/data/utils.py
t5/evaluation/__init__.py
t5/evaluation/eval_utils.py
t5/evaluation/eval_utils_test.py
t5/evaluation/metrics.py
t5/evaluation/metrics_test.py
t5/evaluation/qa_utils.py
t5/evaluation/qa_utils_test.py
t5/evaluation/test_utils.py
t5/models/__init__.py
t5/models/hf_model.py
t5/models/mesh_transformer.py
t5/models/mesh_transformer_main.py
t5/models/mesh_transformer_test.py
t5/models/mtf_model.py
t5/models/t5_model.py
t5/models/utils.py
t5/models/gin/__init__.py
t5/models/gin/beam_search.gin
t5/models/gin/dataset.gin
t5/models/gin/eval.gin
t5/models/gin/greedy_decode.gin
t5/models/gin/infer.gin
t5/models/gin/infer_from_task.gin
t5/models/gin/infer_multi_file.gin
t5/models/gin/perplexity_eval.gin
t5/models/gin/sample_decode.gin
t5/models/gin/score_eval.gin
t5/models/gin/score_from_file.gin
t5/models/gin/score_from_task.gin
t5/models/gin/task_adapter.gin
t5/models/gin/learning_rate_schedules/__init__.py
t5/models/gin/learning_rate_schedules/constant_0_001.gin
t5/models/gin/learning_rate_schedules/rsqrt_no_ramp_down.gin
t5/models/gin/models/__init__.py
t5/models/gin/models/bi_bert_base.gin
t5/models/gin/models/bi_bert_large.gin
t5/models/gin/models/bi_v1.gin
t5/models/gin/models/bi_v1_11B.gin
t5/models/gin/models/bi_v1_2x.gin
t5/models/gin/models/bi_v1_3B.gin
t5/models/gin/models/bi_v1_4x.gin
t5/models/gin/models/bi_v1_l6.gin
t5/models/gin/models/bi_v1_large.gin
t5/models/gin/models/bi_v1_shared.gin
t5/models/gin/models/bi_v1_small.gin
t5/models/gin/models/lm_v1.gin
t5/models/gin/models/lm_v1_ifa.gin
t5/models/gin/models/t5.1.0.11B.gin
t5/models/gin/models/t5.1.0.3B.gin
t5/models/gin/models/t5.1.0.base.gin
t5/models/gin/models/t5.1.0.large.gin
t5-0.9.4.dist-info/LICENSE
t5-0.9.4.dist-info/METADATA
t5-0.9.4.dist-info/WHEEL
t5-0.9.4.dist-info/entry_points.txt
t5-0.9.4.dist-info/top_level.txt
t5-0.9.4.dist-info/RECORD
