Metadata-Version: 2.1
Name: t5
Version: 0.9.4
Summary: Text-to-text transfer transformer
Home-page: http://github.com/google-research/text-to-text-transfer-transformer
Author: Google Inc.
Author-email: no-reply@google.com
License: Apache 2.0
Keywords: text nlp machinelearning
Platform: UNKNOWN
Classifier: Development Status :: 4 - Beta
Classifier: Intended Audience :: Developers
Classifier: Intended Audience :: Science/Research
Classifier: License :: OSI Approved :: Apache Software License
Classifier: Topic :: Scientific/Engineering :: Artificial Intelligence
License-File: LICENSE
Requires-Dist: absl-py
Requires-Dist: babel
Requires-Dist: editdistance
Requires-Dist: immutabledict
Requires-Dist: gin-config
Requires-Dist: mesh-tensorflow[transformer] (>=0.1.13)
Requires-Dist: nltk
Requires-Dist: numpy
Requires-Dist: pandas
Requires-Dist: rouge-score (>=0.1.2)
Requires-Dist: sacrebleu
Requires-Dist: scikit-learn
Requires-Dist: scipy
Requires-Dist: sentencepiece
Requires-Dist: seqio-nightly
Requires-Dist: six (>=1.14)
Requires-Dist: tfds-nightly
Requires-Dist: transformers (>=2.7.0)
Provides-Extra: cache-tasks
Requires-Dist: apache-beam ; extra == 'cache-tasks'
Provides-Extra: gcp
Requires-Dist: gevent ; extra == 'gcp'
Requires-Dist: google-api-python-client ; extra == 'gcp'
Requires-Dist: google-compute-engine ; extra == 'gcp'
Requires-Dist: google-cloud-storage ; extra == 'gcp'
Requires-Dist: oauth2client ; extra == 'gcp'
Provides-Extra: test
Requires-Dist: pytest ; extra == 'test'
Requires-Dist: torch ; extra == 'test'
